2-uart/uart/mUartTx.sv
module mUartTx
#(
    parameter CLOCK_SPEED,
    parameter BAUD_RATE
)
(
    input wire clock,
    output reg uart_tx = 1,

    output reg complete = 1,
    input wire send,

    input wire [7:0] dataIn
);

localparam CLOCK_DELAY = CLOCK_SPEED / BAUD_RATE;

typedef enum {
    TX_STATE_IDLE,
    TX_STATE_DATA
} eTxState;

reg [31:0] clockCounter = 1;
eTxState txState = TX_STATE_IDLE;
reg [7:0] txCounter = 0;

reg [7:0] inputBuf;
reg [7:0] txBuf;
reg shouldSend = 0;

task handleTx();
    begin
        case(txState)
            TX_STATE_IDLE: if(shouldSend) begin // Start bit
                uart_tx <= 0;
                complete <= 0;
                shouldSend <= 0;
                txBuf <= inputBuf;
                txState <= TX_STATE_DATA;
            end
            TX_STATE_DATA: begin // Data
                if(txCounter < 8) begin
                    txCounter <= txCounter + 1;
                    uart_tx <= txBuf[txCounter];
                end else begin
                    txState <= TX_STATE_IDLE;
                    uart_tx <= 1;
                    complete <= 1;
                    txCounter <= 0;
                end
            end
        endcase
    end

endtask

always_ff @( posedge clock )
begin
    if(send) begin
        shouldSend <= 1;
        inputBuf <= dataIn;
    end
    clockCounter <= clockCounter + 1;
    if(clockCounter == CLOCK_DELAY)
    begin
        clockCounter <= 1;

        handleTx();

    end

end

endmodule

2-uart/uart/mUartRx.sv
module mUartRx
#(
    parameter CLOCK_SPEED,
    parameter BAUD_RATE
)
(
    input wire clk,
    input wire uart_rx,

    output reg complete = 0,
    output reg [7:0] dataOut
);

localparam CLOCK_DELAY = CLOCK_SPEED / BAUD_RATE;
localparam START_DELAY = CLOCK_DELAY / 2;
typedef enum {
    RX_STATE_IDLE,
    RX_STATE_DATA
} eRxState;

reg [31:0] clkCounter = 1;
reg [3:0] dataCounter = 0;
eRxState rxState = RX_STATE_IDLE;

always_ff @( posedge clk )
begin

    clkCounter <= clkCounter + 1;
    complete <= 0;
    
    case(rxState)
        RX_STATE_IDLE: if(uart_rx == 0) begin
            if(clkCounter == START_DELAY)
            begin
                rxState <= RX_STATE_DATA;
                clkCounter <= 1;
            end
        end else
            clkCounter <= 1;
        RX_STATE_DATA: if(clkCounter == CLOCK_DELAY) begin
            clkCounter <= 1;

            if(dataCounter < 8) begin
                dataCounter <= dataCounter + 1;
                dataOut <= {uart_rx, dataOut[7:1]};
            end else begin
                complete <= 1;
                dataCounter <= 0;
                rxState <= RX_STATE_IDLE;
            end
        end
    endcase
end

endmodule

2-uart/uart_tb.sv
module test();
  reg clk = 0;
  reg uart_rx = 1;
  wire uart_tx;
  wire complete;
  wire [7:0] rxData;
  wire completeTx;

  always
    #1 clk = ~clk;

  mUartRx #(8, 1) u(clk, uart_rx, complete, rxData);
  mUartTx #(8, 1) u2(clk, uart_tx, completeTx, complete, rxData);

    initial begin
    $display("Starting UART RX");
    $monitor("Complete Value %b", complete);
    for (int i=0; i<100; i=i+1) begin
      #16 uart_rx=0;
      #16 uart_rx=1;
      #16 uart_rx=1;
      #16 uart_rx=1;
      #16 uart_rx=1;
      #16 uart_rx=1;
      #16 uart_rx=1;
      #16 uart_rx=1;
      #16 uart_rx=1;
      #16 uart_rx=1;

      #16 uart_rx=0;
      #16 uart_rx=0;
      #16 uart_rx=0;
      #16 uart_rx=0;
      #16 uart_rx=0;
      #16 uart_rx=0;
      #16 uart_rx=0;
      #16 uart_rx=0;
      #16 uart_rx=0;
      #16 uart_rx=1;
    end
    #1000 $finish;
  end

  initial begin
    $dumpfile("uart.vcd");
    $dumpvars(0,test);
  end

endmodule

2-uart/uart.vcd
$date
	Tue Feb 13 21:48:50 2024
$end
$version
	Icarus Verilog
$end
$timescale
	1s
$end
$scope module test $end
$var wire 1 ! uart_tx $end
$var wire 8 " rxData [7:0] $end
$var wire 1 # completeTx $end
$var wire 1 $ complete $end
$var reg 1 % clk $end
$var reg 1 & uart_rx $end
$scope module u $end
$var wire 1 % clk $end
$var wire 1 & uart_rx $end
$var parameter 32 ' BAUD_RATE $end
$var parameter 32 ( CLOCK_DELAY $end
$var parameter 32 ) CLOCK_SPEED $end
$var parameter 32 * START_DELAY $end
$var reg 32 + clkCounter [31:0] $end
$var reg 1 $ complete $end
$var reg 4 , dataCounter [3:0] $end
$var reg 8 - dataOut [7:0] $end
$var integer 32 . rxState [31:0] $end
$upscope $end
$scope module u2 $end
$var wire 1 % clock $end
$var wire 8 / dataIn [7:0] $end
$var wire 1 $ send $end
$var parameter 32 0 BAUD_RATE $end
$var parameter 32 1 CLOCK_DELAY $end
$var parameter 32 2 CLOCK_SPEED $end
$var reg 32 3 clockCounter [31:0] $end
$var reg 1 # complete $end
$var reg 8 4 inputBuf [7:0] $end
$var reg 1 5 shouldSend $end
$var reg 8 6 txBuf [7:0] $end
$var reg 8 7 txCounter [7:0] $end
$var reg 1 ! uart_tx $end
$var integer 32 8 txState [31:0] $end
$scope task handleTx $end
$upscope $end
$upscope $end
$scope begin $ivl_for_loop0 $end
$var integer 32 9 i [31:0] $end
$upscope $end
$upscope $end
$enddefinitions $end
$comment Show the parameter values. $end
$dumpall
b1000 2
b1000 1
b1 0
b100 *
b1000 )
b1000 (
b1 '
$end
#0
$dumpvars
b0 9
b0 8
b0 7
bx 6
05
bx 4
b1 3
bx /
b0 .
bx -
b0 ,
b1 +
1&
0%
0$
1#
bx "
1!
$end
#1
b1 +
b10 3
1%
#2
0%
#3
b11 3
b1 +
1%
#4
0%
#5
b1 +
b100 3
1%
#6
0%
#7
b101 3
b1 +
1%
#8
0%
#9
b1 +
b110 3
1%
#10
0%
#11
b111 3
b1 +
1%
#12
0%
#13
b1 +
b1000 3
1%
#14
0%
#15
b1 3
b1 +
1%
#16
0%
0&
#17
b10 +
b10 3
1%
#18
0%
#19
b11 3
b11 +
1%
#20
0%
#21
b100 +
b100 3
1%
#22
0%
#23
b101 3
b1 .
b1 +
1%
#24
0%
#25
b10 +
b110 3
1%
#26
0%
#27
b111 3
b11 +
1%
#28
0%
#29
b100 +
b1000 3
1%
#30
0%
#31
b1 3
b101 +
1%
#32
0%
1&
#33
b110 +
b10 3
1%
#34
0%
#35
b11 3
b111 +
1%
#36
0%
#37
b1000 +
b100 3
1%
#38
0%
#39
b101 3
b1xxxxxxx "
b1xxxxxxx -
b1xxxxxxx /
b1 ,
b1 +
1%
#40
0%
#41
b10 +
b110 3
1%
#42
0%
#43
b111 3
b11 +
1%
#44
0%
#45
b100 +
b1000 3
1%
#46
0%
#47
b1 3
b101 +
1%
#48
0%
#49
b110 +
b10 3
1%
#50
0%
#51
b11 3
b111 +
1%
#52
0%
#53
b1000 +
b100 3
1%
#54
0%
#55
b101 3
b11xxxxxx "
b11xxxxxx -
b11xxxxxx /
b10 ,
b1 +
1%
#56
0%
#57
b10 +
b110 3
1%
#58
0%
#59
b111 3
b11 +
1%
#60
0%
#61
b100 +
b1000 3
1%
#62
0%
#63
b1 3
b101 +
1%
#64
0%
#65
b110 +
b10 3
1%
#66
0%
#67
b11 3
b111 +
1%
#68
0%
#69
b1000 +
b100 3
1%
#70
0%
#71
b101 3
b111xxxxx "
b111xxxxx -
b111xxxxx /
b11 ,
b1 +
1%
#72
0%
#73
b10 +
b110 3
1%
#74
0%
#75
b111 3
b11 +
1%
#76
0%
#77
b100 +
b1000 3
1%
#78
0%
#79
b1 3
b101 +
1%
#80
0%
#81
b110 +
b10 3
1%
#82
0%
#83
b11 3
b111 +
1%
#84
0%
#85
b1000 +
b100 3
1%
#86
0%
#87
b101 3
b1111xxxx "
b1111xxxx -
b1111xxxx /
b100 ,
b1 +
1%
#88
0%
#89
b10 +
b110 3
1%
#90
0%
#91
b111 3
b11 +
1%
#92
0%
#93
b100 +
b1000 3
1%
#94
0%
#95
b1 3
b101 +
1%
#96
0%
#97
b110 +
b10 3
1%
#98
0%
#99
b11 3
b111 +
1%
#100
0%
#101
b1000 +
b100 3
1%
#102
0%
#103
b101 3
b11111xxx "
b11111xxx -
b11111xxx /
b101 ,
b1 +
1%
#104
0%
#105
b10 +
b110 3
1%
#106
0%
#107
b111 3
b11 +
1%
#108
0%
#109
b100 +
b1000 3
1%
#110
0%
#111
b1 3
b101 +
1%
#112
0%
#113
b110 +
b10 3
1%
#114
0%
#115
b11 3
b111 +
1%
#116
0%
#117
b1000 +
b100 3
1%
#118
0%
#119
b101 3
b111111xx "
b111111xx -
b111111xx /
b110 ,
b1 +
1%
#120
0%
#121
b10 +
b110 3
1%
#122
0%
#123
b111 3
b11 +
1%
#124
0%
#125
b100 +
b1000 3
1%
#126
0%
#127
b1 3
b101 +
1%
#128
0%
#129
b110 +
b10 3
1%
#130
0%
#131
b11 3
b111 +
1%
#132
0%
#133
b1000 +
b100 3
1%
#134
0%
#135
b101 3
b1111111x "
b1111111x -
b1111111x /
b111 ,
b1 +
1%
#136
0%
#137
b10 +
b110 3
1%
#138
0%
#139
b111 3
b11 +
1%
#140
0%
#141
b100 +
b1000 3
1%
#142
0%
#143
b1 3
b101 +
1%
#144
0%
#145
b110 +
b10 3
1%
#146
0%
#147
b11 3
b111 +
1%
#148
0%
#149
b1000 +
b100 3
1%
#150
0%
#151
b101 3
b11111111 "
b11111111 -
b11111111 /
b1000 ,
b1 +
1%
#152
0%
#153
b10 +
b110 3
1%
#154
0%
#155
b111 3
b11 +
1%
#156
0%
#157
b100 +
b1000 3
1%
#158
0%
#159
b1 3
b101 +
1%
#160
0%
#161
b110 +
b10 3
1%
#162
0%
#163
b11 3
b111 +
1%
#164
0%
#165
b1000 +
b100 3
1%
#166
0%
#167
b101 3
b0 .
b0 ,
1$
b1 +
1%
#168
0%
#169
0$
b1 +
b110 3
b11111111 4
15
1%
#170
0%
#171
b111 3
b1 +
1%
#172
0%
#173
b1 +
b1000 3
1%
#174
0%
#175
b1 8
b11111111 6
05
0#
0!
b1 3
b1 +
1%
#176
0%
0&
#177
b10 +
b10 3
1%
#178
0%
#179
b11 3
b11 +
1%
#180
0%
#181
b100 +
b100 3
1%
#182
0%
#183
b101 3
b1 .
b1 +
1%
#184
0%
#185
b10 +
b110 3
1%
#186
0%
#187
b111 3
b11 +
1%
#188
0%
#189
b100 +
b1000 3
1%
#190
0%
#191
1!
b1 7
b1 3
b101 +
1%
#192
0%
#193
b110 +
b10 3
1%
#194
0%
#195
b11 3
b111 +
1%
#196
0%
#197
b1000 +
b100 3
1%
#198
0%
#199
b101 3
b1111111 "
b1111111 -
b1111111 /
b1 ,
b1 +
1%
#200
0%
#201
b10 +
b110 3
1%
#202
0%
#203
b111 3
b11 +
1%
#204
0%
#205
b100 +
b1000 3
1%
#206
0%
#207
b10 7
b1 3
b101 +
1%
#208
0%
#209
b110 +
b10 3
1%
#210
0%
#211
b11 3
b111 +
1%
#212
0%
#213
b1000 +
b100 3
1%
#214
0%
#215
b101 3
b111111 "
b111111 -
b111111 /
b10 ,
b1 +
1%
#216
0%
#217
b10 +
b110 3
1%
#218
0%
#219
b111 3
b11 +
1%
#220
0%
#221
b100 +
b1000 3
1%
#222
0%
#223
b11 7
b1 3
b101 +
1%
#224
0%
#225
b110 +
b10 3
1%
#226
0%
#227
b11 3
b111 +
1%
#228
0%
#229
b1000 +
b100 3
1%
#230
0%
#231
b101 3
b11111 "
b11111 -
b11111 /
b11 ,
b1 +
1%
#232
0%
#233
b10 +
b110 3
1%
#234
0%
#235
b111 3
b11 +
1%
#236
0%
#237
b100 +
b1000 3
1%
#238
0%
#239
b100 7
b1 3
b101 +
1%
#240
0%
#241
b110 +
b10 3
1%
#242
0%
#243
b11 3
b111 +
1%
#244
0%
#245
b1000 +
b100 3
1%
#246
0%
#247
b101 3
b1111 "
b1111 -
b1111 /
b100 ,
b1 +
1%
#248
0%
#249
b10 +
b110 3
1%
#250
0%
#251
b111 3
b11 +
1%
#252
0%
#253
b100 +
b1000 3
1%
#254
0%
#255
b101 7
b1 3
b101 +
1%
#256
0%
#257
b110 +
b10 3
1%
#258
0%
#259
b11 3
b111 +
1%
#260
0%
#261
b1000 +
b100 3
1%
#262
0%
#263
b101 3
b111 "
b111 -
b111 /
b101 ,
b1 +
1%
#264
0%
#265
b10 +
b110 3
1%
#266
0%
#267
b111 3
b11 +
1%
#268
0%
#269
b100 +
b1000 3
1%
#270
0%
#271
b110 7
b1 3
b101 +
1%
#272
0%
#273
b110 +
b10 3
1%
#274
0%
#275
b11 3
b111 +
1%
#276
0%
#277
b1000 +
b100 3
1%
#278
0%
#279
b101 3
b11 "
b11 -
b11 /
b110 ,
b1 +
1%
#280
0%
#281
b10 +
b110 3
1%
#282
0%
#283
b111 3
b11 +
1%
#284
0%
#285
b100 +
b1000 3
1%
#286
0%
#287
b111 7
b1 3
b101 +
1%
#288
0%
#289
b110 +
b10 3
1%
#290
0%
#291
b11 3
b111 +
1%
#292
0%
#293
b1000 +
b100 3
1%
#294
0%
#295
b101 3
b1 "
b1 -
b1 /
b111 ,
b1 +
1%
#296
0%
#297
b10 +
b110 3
1%
#298
0%
#299
b111 3
b11 +
1%
#300
0%
#301
b100 +
b1000 3
1%
#302
0%
#303
b1000 7
b1 3
b101 +
1%
#304
0%
#305
b110 +
b10 3
1%
#306
0%
#307
b11 3
b111 +
1%
#308
0%
#309
b1000 +
b100 3
1%
#310
0%
#311
b101 3
b0 "
b0 -
b0 /
b1000 ,
b1 +
1%
#312
0%
#313
b10 +
b110 3
1%
#314
0%
#315
b111 3
b11 +
1%
#316
0%
#317
b100 +
b1000 3
1%
#318
0%
#319
b0 7
1#
b0 8
b1 3
b101 +
1%
#320
0%
b1 9
1&
#321
b110 +
b10 3
1%
#322
0%
#323
b11 3
b111 +
1%
#324
0%
#325
b1000 +
b100 3
1%
#326
0%
#327
b101 3
b0 .
b0 ,
1$
b1 +
1%
#328
0%
#329
0$
b1 +
b110 3
b0 4
15
1%
#330
0%
#331
b111 3
b1 +
1%
#332
0%
#333
b1 +
b1000 3
1%
#334
0%
#335
b1 8
b0 6
05
0#
0!
b1 3
b1 +
1%
#336
0%
0&
#337
b10 +
b10 3
1%
#338
0%
#339
b11 3
b11 +
1%
#340
0%
#341
b100 +
b100 3
1%
#342
0%
#343
b101 3
b1 .
b1 +
1%
#344
0%
#345
b10 +
b110 3
1%
#346
0%
#347
b111 3
b11 +
1%
#348
0%
#349
b100 +
b1000 3
1%
#350
0%
#351
b1 7
b1 3
b101 +
1%
#352
0%
1&
#353
b110 +
b10 3
1%
#354
0%
#355
b11 3
b111 +
1%
#356
0%
#357
b1000 +
b100 3
1%
#358
0%
#359
b101 3
b10000000 "
b10000000 -
b10000000 /
b1 ,
b1 +
1%
#360
0%
#361
b10 +
b110 3
1%
#362
0%
#363
b111 3
b11 +
1%
#364
0%
#365
b100 +
b1000 3
1%
#366
0%
#367
b10 7
b1 3
b101 +
1%
#368
0%
#369
b110 +
b10 3
1%
#370
0%
#371
b11 3
b111 +
1%
#372
0%
#373
b1000 +
b100 3
1%
#374
0%
#375
b101 3
b11000000 "
b11000000 -
b11000000 /
b10 ,
b1 +
1%
#376
0%
#377
b10 +
b110 3
1%
#378
0%
#379
b111 3
b11 +
1%
#380
0%
#381
b100 +
b1000 3
1%
#382
0%
#383
b11 7
b1 3
b101 +
1%
#384
0%
#385
b110 +
b10 3
1%
#386
0%
#387
b11 3
b111 +
1%
#388
0%
#389
b1000 +
b100 3
1%
#390
0%
#391
b101 3
b11100000 "
b11100000 -
b11100000 /
b11 ,
b1 +
1%
#392
0%
#393
b10 +
b110 3
1%
#394
0%
#395
b111 3
b11 +
1%
#396
0%
#397
b100 +
b1000 3
1%
#398
0%
#399
b100 7
b1 3
b101 +
1%
#400
0%
#401
b110 +
b10 3
1%
#402
0%
#403
b11 3
b111 +
1%
#404
0%
#405
b1000 +
b100 3
1%
#406
0%
#407
b101 3
b11110000 "
b11110000 -
b11110000 /
b100 ,
b1 +
1%
#408
0%
#409
b10 +
b110 3
1%
#410
0%
#411
b111 3
b11 +
1%
#412
0%
#413
b100 +
b1000 3
1%
#414
0%
#415
b101 7
b1 3
b101 +
1%
#416
0%
#417
b110 +
b10 3
1%
#418
0%
#419
b11 3
b111 +
1%
#420
0%
#421
b1000 +
b100 3
1%
#422
0%
#423
b101 3
b11111000 "
b11111000 -
b11111000 /
b101 ,
b1 +
1%
#424
0%
#425
b10 +
b110 3
1%
#426
0%
#427
b111 3
b11 +
1%
#428
0%
#429
b100 +
b1000 3
1%
#430
0%
#431
b110 7
b1 3
b101 +
1%
#432
0%
#433
b110 +
b10 3
1%
#434
0%
#435
b11 3
b111 +
1%
#436
0%
#437
b1000 +
b100 3
1%
#438
0%
#439
b101 3
b11111100 "
b11111100 -
b11111100 /
b110 ,
b1 +
1%
#440
0%
#441
b10 +
b110 3
1%
#442
0%
#443
b111 3
b11 +
1%
#444
0%
#445
b100 +
b1000 3
1%
#446
0%
#447
b111 7
b1 3
b101 +
1%
#448
0%
#449
b110 +
b10 3
1%
#450
0%
#451
b11 3
b111 +
1%
#452
0%
#453
b1000 +
b100 3
1%
#454
0%
#455
b101 3
b11111110 "
b11111110 -
b11111110 /
b111 ,
b1 +
1%
#456
0%
#457
b10 +
b110 3
1%
#458
0%
#459
b111 3
b11 +
1%
#460
0%
#461
b100 +
b1000 3
1%
#462
0%
#463
b1000 7
b1 3
b101 +
1%
#464
0%
#465
b110 +
b10 3
1%
#466
0%
#467
b11 3
b111 +
1%
#468
0%
#469
b1000 +
b100 3
1%
#470
0%
#471
b101 3
b11111111 "
b11111111 -
b11111111 /
b1000 ,
b1 +
1%
#472
0%
#473
b10 +
b110 3
1%
#474
0%
#475
b111 3
b11 +
1%
#476
0%
#477
b100 +
b1000 3
1%
#478
0%
#479
b0 7
1#
1!
b0 8
b1 3
b101 +
1%
#480
0%
#481
b110 +
b10 3
1%
#482
0%
#483
b11 3
b111 +
1%
#484
0%
#485
b1000 +
b100 3
1%
#486
0%
#487
b101 3
b0 .
b0 ,
1$
b1 +
1%
#488
0%
#489
0$
b1 +
b110 3
b11111111 4
15
1%
#490
0%
#491
b111 3
b1 +
1%
#492
0%
#493
b1 +
b1000 3
1%
#494
0%
#495
b1 8
b11111111 6
05
0#
0!
b1 3
b1 +
1%
#496
0%
0&
#497
b10 +
b10 3
1%
#498
0%
#499
b11 3
b11 +
1%
#500
0%
#501
b100 +
b100 3
1%
#502
0%
#503
b101 3
b1 .
b1 +
1%
#504
0%
#505
b10 +
b110 3
1%
#506
0%
#507
b111 3
b11 +
1%
#508
0%
#509
b100 +
b1000 3
1%
#510
0%
#511
1!
b1 7
b1 3
b101 +
1%
#512
0%
#513
b110 +
b10 3
1%
#514
0%
#515
b11 3
b111 +
1%
#516
0%
#517
b1000 +
b100 3
1%
#518
0%
#519
b101 3
b1111111 "
b1111111 -
b1111111 /
b1 ,
b1 +
1%
#520
0%
#521
b10 +
b110 3
1%
#522
0%
#523
b111 3
b11 +
1%
#524
0%
#525
b100 +
b1000 3
1%
#526
0%
#527
b10 7
b1 3
b101 +
1%
#528
0%
#529
b110 +
b10 3
1%
#530
0%
#531
b11 3
b111 +
1%
#532
0%
#533
b1000 +
b100 3
1%
#534
0%
#535
b101 3
b111111 "
b111111 -
b111111 /
b10 ,
b1 +
1%
#536
0%
#537
b10 +
b110 3
1%
#538
0%
#539
b111 3
b11 +
1%
#540
0%
#541
b100 +
b1000 3
1%
#542
0%
#543
b11 7
b1 3
b101 +
1%
#544
0%
#545
b110 +
b10 3
1%
#546
0%
#547
b11 3
b111 +
1%
#548
0%
#549
b1000 +
b100 3
1%
#550
0%
#551
b101 3
b11111 "
b11111 -
b11111 /
b11 ,
b1 +
1%
#552
0%
#553
b10 +
b110 3
1%
#554
0%
#555
b111 3
b11 +
1%
#556
0%
#557
b100 +
b1000 3
1%
#558
0%
#559
b100 7
b1 3
b101 +
1%
#560
0%
#561
b110 +
b10 3
1%
#562
0%
#563
b11 3
b111 +
1%
#564
0%
#565
b1000 +
b100 3
1%
#566
0%
#567
b101 3
b1111 "
b1111 -
b1111 /
b100 ,
b1 +
1%
#568
0%
#569
b10 +
b110 3
1%
#570
0%
#571
b111 3
b11 +
1%
#572
0%
#573
b100 +
b1000 3
1%
#574
0%
#575
b101 7
b1 3
b101 +
1%
#576
0%
#577
b110 +
b10 3
1%
#578
0%
#579
b11 3
b111 +
1%
#580
0%
#581
b1000 +
b100 3
1%
#582
0%
#583
b101 3
b111 "
b111 -
b111 /
b101 ,
b1 +
1%
#584
0%
#585
b10 +
b110 3
1%
#586
0%
#587
b111 3
b11 +
1%
#588
0%
#589
b100 +
b1000 3
1%
#590
0%
#591
b110 7
b1 3
b101 +
1%
#592
0%
#593
b110 +
b10 3
1%
#594
0%
#595
b11 3
b111 +
1%
#596
0%
#597
b1000 +
b100 3
1%
#598
0%
#599
b101 3
b11 "
b11 -
b11 /
b110 ,
b1 +
1%
#600
0%
#601
b10 +
b110 3
1%
#602
0%
#603
b111 3
b11 +
1%
#604
0%
#605
b100 +
b1000 3
1%
#606
0%
#607
b111 7
b1 3
b101 +
1%
#608
0%
#609
b110 +
b10 3
1%
#610
0%
#611
b11 3
b111 +
1%
#612
0%
#613
b1000 +
b100 3
1%
#614
0%
#615
b101 3
b1 "
b1 -
b1 /
b111 ,
b1 +
1%
#616
0%
#617
b10 +
b110 3
1%
#618
0%
#619
b111 3
b11 +
1%
#620
0%
#621
b100 +
b1000 3
1%
#622
0%
#623
b1000 7
b1 3
b101 +
1%
#624
0%
#625
b110 +
b10 3
1%
#626
0%
#627
b11 3
b111 +
1%
#628
0%
#629
b1000 +
b100 3
1%
#630
0%
#631
b101 3
b0 "
b0 -
b0 /
b1000 ,
b1 +
1%
#632
0%
#633
b10 +
b110 3
1%
#634
0%
#635
b111 3
b11 +
1%
#636
0%
#637
b100 +
b1000 3
1%
#638
0%
#639
b0 7
1#
b0 8
b1 3
b101 +
1%
#640
0%
b10 9
1&
#641
b110 +
b10 3
1%
#642
0%
#643
b11 3
b111 +
1%
#644
0%
#645
b1000 +
b100 3
1%
#646
0%
#647
b101 3
b0 .
b0 ,
1$
b1 +
1%
#648
0%
#649
0$
b1 +
b110 3
b0 4
15
1%
#650
0%
#651
b111 3
b1 +
1%
#652
0%
#653
b1 +
b1000 3
1%
#654
0%
#655
b1 8
b0 6
05
0#
0!
b1 3
b1 +
1%
#656
0%
0&
#657
b10 +
b10 3
1%
#658
0%
#659
b11 3
b11 +
1%
#660
0%
#661
b100 +
b100 3
1%
#662
0%
#663
b101 3
b1 .
b1 +
1%
#664
0%
#665
b10 +
b110 3
1%
#666
0%
#667
b111 3
b11 +
1%
#668
0%
#669
b100 +
b1000 3
1%
#670
0%
#671
b1 7
b1 3
b101 +
1%
#672
0%
1&
#673
b110 +
b10 3
1%
#674
0%
#675
b11 3
b111 +
1%
#676
0%
#677
b1000 +
b100 3
1%
#678
0%
#679
b101 3
b10000000 "
b10000000 -
b10000000 /
b1 ,
b1 +
1%
#680
0%
#681
b10 +
b110 3
1%
#682
0%
#683
b111 3
b11 +
1%
#684
0%
#685
b100 +
b1000 3
1%
#686
0%
#687
b10 7
b1 3
b101 +
1%
#688
0%
#689
b110 +
b10 3
1%
#690
0%
#691
b11 3
b111 +
1%
#692
0%
#693
b1000 +
b100 3
1%
#694
0%
#695
b101 3
b11000000 "
b11000000 -
b11000000 /
b10 ,
b1 +
1%
#696
0%
#697
b10 +
b110 3
1%
#698
0%
#699
b111 3
b11 +
1%
#700
0%
#701
b100 +
b1000 3
1%
#702
0%
#703
b11 7
b1 3
b101 +
1%
#704
0%
#705
b110 +
b10 3
1%
#706
0%
#707
b11 3
b111 +
1%
#708
0%
#709
b1000 +
b100 3
1%
#710
0%
#711
b101 3
b11100000 "
b11100000 -
b11100000 /
b11 ,
b1 +
1%
#712
0%
#713
b10 +
b110 3
1%
#714
0%
#715
b111 3
b11 +
1%
#716
0%
#717
b100 +
b1000 3
1%
#718
0%
#719
b100 7
b1 3
b101 +
1%
#720
0%
#721
b110 +
b10 3
1%
#722
0%
#723
b11 3
b111 +
1%
#724
0%
#725
b1000 +
b100 3
1%
#726
0%
#727
b101 3
b11110000 "
b11110000 -
b11110000 /
b100 ,
b1 +
1%
#728
0%
#729
b10 +
b110 3
1%
#730
0%
#731
b111 3
b11 +
1%
#732
0%
#733
b100 +
b1000 3
1%
#734
0%
#735
b101 7
b1 3
b101 +
1%
#736
0%
#737
b110 +
b10 3
1%
#738
0%
#739
b11 3
b111 +
1%
#740
0%
#741
b1000 +
b100 3
1%
#742
0%
#743
b101 3
b11111000 "
b11111000 -
b11111000 /
b101 ,
b1 +
1%
#744
0%
#745
b10 +
b110 3
1%
#746
0%
#747
b111 3
b11 +
1%
#748
0%
#749
b100 +
b1000 3
1%
#750
0%
#751
b110 7
b1 3
b101 +
1%
#752
0%
#753
b110 +
b10 3
1%
#754
0%
#755
b11 3
b111 +
1%
#756
0%
#757
b1000 +
b100 3
1%
#758
0%
#759
b101 3
b11111100 "
b11111100 -
b11111100 /
b110 ,
b1 +
1%
#760
0%
#761
b10 +
b110 3
1%
#762
0%
#763
b111 3
b11 +
1%
#764
0%
#765
b100 +
b1000 3
1%
#766
0%
#767
b111 7
b1 3
b101 +
1%
#768
0%
#769
b110 +
b10 3
1%
#770
0%
#771
b11 3
b111 +
1%
#772
0%
#773
b1000 +
b100 3
1%
#774
0%
#775
b101 3
b11111110 "
b11111110 -
b11111110 /
b111 ,
b1 +
1%
#776
0%
#777
b10 +
b110 3
1%
#778
0%
#779
b111 3
b11 +
1%
#780
0%
#781
b100 +
b1000 3
1%
#782
0%
#783
b1000 7
b1 3
b101 +
1%
#784
0%
#785
b110 +
b10 3
1%
#786
0%
#787
b11 3
b111 +
1%
#788
0%
#789
b1000 +
b100 3
1%
#790
0%
#791
b101 3
b11111111 "
b11111111 -
b11111111 /
b1000 ,
b1 +
1%
#792
0%
#793
b10 +
b110 3
1%
#794
0%
#795
b111 3
b11 +
1%
#796
0%
#797
b100 +
b1000 3
1%
#798
0%
#799
b0 7
1#
1!
b0 8
b1 3
b101 +
1%
#800
0%
#801
b110 +
b10 3
1%
#802
0%
#803
b11 3
b111 +
1%
#804
0%
#805
b1000 +
b100 3
1%
#806
0%
#807
b101 3
b0 .
b0 ,
1$
b1 +
1%
#808
0%
#809
0$
b1 +
b110 3
b11111111 4
15
1%
#810
0%
#811
b111 3
b1 +
1%
#812
0%
#813
b1 +
b1000 3
1%
#814
0%
#815
b1 8
b11111111 6
05
0#
0!
b1 3
b1 +
1%
#816
0%
0&
#817
b10 +
b10 3
1%
#818
0%
#819
b11 3
b11 +
1%
#820
0%
#821
b100 +
b100 3
1%
#822
0%
#823
b101 3
b1 .
b1 +
1%
#824
0%
#825
b10 +
b110 3
1%
#826
0%
#827
b111 3
b11 +
1%
#828
0%
#829
b100 +
b1000 3
1%
#830
0%
#831
1!
b1 7
b1 3
b101 +
1%
#832
0%
#833
b110 +
b10 3
1%
#834
0%
#835
b11 3
b111 +
1%
#836
0%
#837
b1000 +
b100 3
1%
#838
0%
#839
b101 3
b1111111 "
b1111111 -
b1111111 /
b1 ,
b1 +
1%
#840
0%
#841
b10 +
b110 3
1%
#842
0%
#843
b111 3
b11 +
1%
#844
0%
#845
b100 +
b1000 3
1%
#846
0%
#847
b10 7
b1 3
b101 +
1%
#848
0%
#849
b110 +
b10 3
1%
#850
0%
#851
b11 3
b111 +
1%
#852
0%
#853
b1000 +
b100 3
1%
#854
0%
#855
b101 3
b111111 "
b111111 -
b111111 /
b10 ,
b1 +
1%
#856
0%
#857
b10 +
b110 3
1%
#858
0%
#859
b111 3
b11 +
1%
#860
0%
#861
b100 +
b1000 3
1%
#862
0%
#863
b11 7
b1 3
b101 +
1%
#864
0%
#865
b110 +
b10 3
1%
#866
0%
#867
b11 3
b111 +
1%
#868
0%
#869
b1000 +
b100 3
1%
#870
0%
#871
b101 3
b11111 "
b11111 -
b11111 /
b11 ,
b1 +
1%
#872
0%
#873
b10 +
b110 3
1%
#874
0%
#875
b111 3
b11 +
1%
#876
0%
#877
b100 +
b1000 3
1%
#878
0%
#879
b100 7
b1 3
b101 +
1%
#880
0%
#881
b110 +
b10 3
1%
#882
0%
#883
b11 3
b111 +
1%
#884
0%
#885
b1000 +
b100 3
1%
#886
0%
#887
b101 3
b1111 "
b1111 -
b1111 /
b100 ,
b1 +
1%
#888
0%
#889
b10 +
b110 3
1%
#890
0%
#891
b111 3
b11 +
1%
#892
0%
#893
b100 +
b1000 3
1%
#894
0%
#895
b101 7
b1 3
b101 +
1%
#896
0%
#897
b110 +
b10 3
1%
#898
0%
#899
b11 3
b111 +
1%
#900
0%
#901
b1000 +
b100 3
1%
#902
0%
#903
b101 3
b111 "
b111 -
b111 /
b101 ,
b1 +
1%
#904
0%
#905
b10 +
b110 3
1%
#906
0%
#907
b111 3
b11 +
1%
#908
0%
#909
b100 +
b1000 3
1%
#910
0%
#911
b110 7
b1 3
b101 +
1%
#912
0%
#913
b110 +
b10 3
1%
#914
0%
#915
b11 3
b111 +
1%
#916
0%
#917
b1000 +
b100 3
1%
#918
0%
#919
b101 3
b11 "
b11 -
b11 /
b110 ,
b1 +
1%
#920
0%
#921
b10 +
b110 3
1%
#922
0%
#923
b111 3
b11 +
1%
#924
0%
#925
b100 +
b1000 3
1%
#926
0%
#927
b111 7
b1 3
b101 +
1%
#928
0%
#929
b110 +
b10 3
1%
#930
0%
#931
b11 3
b111 +
1%
#932
0%
#933
b1000 +
b100 3
1%
#934
0%
#935
b101 3
b1 "
b1 -
b1 /
b111 ,
b1 +
1%
#936
0%
#937
b10 +
b110 3
1%
#938
0%
#939
b111 3
b11 +
1%
#940
0%
#941
b100 +
b1000 3
1%
#942
0%
#943
b1000 7
b1 3
b101 +
1%
#944
0%
#945
b110 +
b10 3
1%
#946
0%
